python_utils/__init__.py
python_utils/decorators/__init__.py
python_utils/decorators/utils.py
python_utils/logging/__init__.py
python_utils/logging/logging.py
python_utils_traveler-0.0.14.dist-info/LICENSE
python_utils_traveler-0.0.14.dist-info/METADATA
python_utils_traveler-0.0.14.dist-info/WHEEL
python_utils_traveler-0.0.14.dist-info/RECORD
