Metadata-Version: 2.3
Name: python-utils-traveler
Version: 0.0.14
Summary: Personal python utilities
Author: Ryan Bui
Author-email: ryan.bui@gmail.com
Requires-Python: >=3.10,<4.0
Classifier: Programming Language :: Python :: 3
Classifier: Programming Language :: Python :: 3.10
Classifier: Programming Language :: Python :: 3.11
Classifier: Programming Language :: Python :: 3.12
Classifier: Programming Language :: Python :: 3.13
